Metadata-Version: 2.2
Name: phenopype
Version: 6.1.0
Summary: A phenotyping pipeline for python
Author-email: Moritz Lürig <moritz.luerig@gmail.com>
License:                    GNU LESSER GENERAL PUBLIC LICENSE
Project-URL: Homepage, https://www.phenopype.org
Project-URL: Documentation, https://www.phenopype.org/docs/
Project-URL: Repository, https://github.com/phenopype/phenopype
Project-URL: Bug Tracker, https://github.com/phenopype/phenopype/issues
Keywords: computer vision,biology,ecology,evolution
Requires-Python: >=3.9
License-File: LICENSE
Requires-Dist: colour
Requires-Dist: numpy
Requires-Dist: opencv-contrib-python
Requires-Dist: pandas
Requires-Dist: pillow
Requires-Dist: ruamel.yaml
Requires-Dist: tqdm
Requires-Dist: rich
Requires-Dist: screeninfo
Requires-Dist: watchdog
Provides-Extra: test
Requires-Dist: pytest; extra == "test"
Requires-Dist: coverage; extra == "test"
Requires-Dist: coveralls; extra == "test"
Requires-Dist: mock; extra == "test"
Requires-Dist: pytest-xvfb; extra == "test"
Requires-Dist: pytest-cov; extra == "test"
Requires-Dist: pyyaml; extra == "test"
